dinjo/__init__.py
dinjo/model.py
dinjo/optimizer.py
dinjo/predefined/__init__.py
dinjo/predefined/epidemiology/__init__.py
dinjo/predefined/epidemiology/_seir_model.py
dinjo/predefined/epidemiology/_seirv_fixed.py
dinjo/predefined/epidemiology/_seirv_model.py
dinjo/predefined/epidemiology/_sir_model.py
dinjo/predefined/physics/__init__.py
dinjo/predefined/physics/_harmonic_oscillator.py
dinjo-0.1.1.dist-info/AUTHORS
dinjo-0.1.1.dist-info/LICENSE
dinjo-0.1.1.dist-info/METADATA
dinjo-0.1.1.dist-info/WHEEL
dinjo-0.1.1.dist-info/top_level.txt
dinjo-0.1.1.dist-info/RECORD
