Metadata-Version: 2.1
Name: dinjo
Version: 0.1.1
Summary: DINJO lets you find optimal values of initial value problems´ parameters
Home-page: https://github.com/fenfisdi/dinjo
Author: Juan Esteban Aristizabal-Zuluaga
Author-email: jeaz.git@gmail.com
License: gplv3
Download-URL: https://github.com/fenfisdi/dinjo/archive/refs/tags/0.1.0.tar.gz
Project-URL: Documentation, https://dinjo.readthedocs.io/
Platform: UNKNOWN
Classifier: Programming Language :: Python :: 3
Classifier: Programming Language :: Python :: 3.8
Classifier: Programming Language :: Python :: 3.9
Classifier: Programming Language :: Python :: 3.10
Classifier: Intended Audience :: Science/Research
Classifier: License :: OSI Approved :: GNU General Public License v3 (GPLv3)
Classifier: Topic :: Scientific/Engineering
Classifier: Topic :: Scientific/Engineering :: Mathematics
Classifier: Development Status :: 3 - Alpha
Classifier: Topic :: Software Development :: Libraries :: Python Modules
Classifier: Topic :: Software Development :: Libraries
Classifier: Topic :: Software Development
Requires-Python: >=3.8
License-File: LICENSE
License-File: AUTHORS
Requires-Dist: numpy (==1.20.3)
Requires-Dist: scipy (==1.6.3)
